pyEDAkit/IntrinsicDimensionality.py
pyEDAkit/__init__.py
pyEDAkit/clustering.py
pyEDAkit/generic_tests.py
pyEDAkit/linear.py
pyEDAkit/non-linear.py
pyEDAkit/standardization.py
pyEDAkit-0.1.4.dist-info/LICENSE
pyEDAkit-0.1.4.dist-info/METADATA
pyEDAkit-0.1.4.dist-info/WHEEL
pyEDAkit-0.1.4.dist-info/top_level.txt
pyEDAkit-0.1.4.dist-info/RECORD
