Metadata-Version: 2.2
Name: pyEDAkit
Version: 0.1.4
Summary: A toolkit for exploratory data analysis in Python
Author-email: Alberto Biscalchin <biscalchin.mau.se@gmail.com>, Marco Schivo <marcoschivo1@gmail.com>
License: MIT License
Project-URL: homepage, https://github.com/zkivo/pyEDAkit
Project-URL: repository, https://github.com/zkivo/pyEDAkit
Keywords: data analysis,EDA,machine learning
Classifier: Programming Language :: Python :: 3
Classifier: License :: OSI Approved :: MIT License
Classifier: Operating System :: OS Independent
Classifier: Topic :: Scientific/Engineering
Classifier: Topic :: Scientific/Engineering :: Information Analysis
Requires-Python: >=3.7
License-File: LICENSE
Requires-Dist: numpy>=1.21.0
Requires-Dist: scipy>=1.7.0
Requires-Dist: matplotlib>=3.4.0
Requires-Dist: scikit-learn>=0.24.0
Requires-Dist: pandas>=1.3.0
Requires-Dist: networkx>=2.5
